{
    "script_ver": 1.0,
    "entities": [
        {
            "id": 1,
            "name": "I:/Pro.soft/ENRE/ENRE-py/tests/cases/_anonymousfunction/_anonymousfunctiondefinition/test_anonymous.py",
            "type": "FILE",
            "belongs_to": null,
            "line": -1,
            "start_column": -1,
            "end_column": -1
        },
        {
            "id": 2,
            "name": "test_anonymous",
            "type": "MODULE",
            "belongs_to": null,
            "line": -1,
            "start_column": -1,
            "end_column": -1
        }
    ],
    "relations": [],
    "db_name": "anonymousfunctiondefinition"
}